context_compose/__init__.py
context_compose-0.0.2.dist-info/LICENSE
context_compose-0.0.2.dist-info/METADATA
context_compose-0.0.2.dist-info/WHEEL
context_compose-0.0.2.dist-info/top_level.txt
context_compose-0.0.2.dist-info/RECORD
