Metadata-Version: 2.1
Name: context-compose
Version: 0.0.2
Summary: Compose context managers from a sequence
Home-page: https://github.com/jackric/context_compose
Author: Jack Riches
Author-email: jackriches@gmail.com
License: UNKNOWN
Platform: UNKNOWN
Classifier: Programming Language :: Python :: 3
Classifier: License :: OSI Approved :: MIT License
Classifier: Operating System :: OS Independent
Requires-Python: >=3.6
